pytest_pyright/__init__.py
pytest_pyright/_compat.py
pytest_pyright/models.py
pytest_pyright/plugin.py
pytest_pyright-0.0.6.dist-info/LICENSE
pytest_pyright-0.0.6.dist-info/METADATA
pytest_pyright-0.0.6.dist-info/WHEEL
pytest_pyright-0.0.6.dist-info/entry_points.txt
pytest_pyright-0.0.6.dist-info/top_level.txt
pytest_pyright-0.0.6.dist-info/RECORD
