Metadata-Version: 2.1
Name: pytest-pyright
Version: 0.0.6
Summary: Pytest plugin for type checking code with Pyright
Home-page: https://github.com/RobertCraigie/pytest-pyright
Author: Robert Craigie
Author-email: robertcraigie30@gmail.com
Maintainer: Robert Craigie
Maintainer-email: robertcraigie30@gmail.com
License: MIT
Classifier: Development Status :: 4 - Beta
Classifier: Framework :: Pytest
Classifier: Intended Audience :: Developers
Classifier: Topic :: Software Development :: Testing
Classifier: Programming Language :: Python
Classifier: Programming Language :: Python :: 3
Classifier: Programming Language :: Python :: 3.6
Classifier: Programming Language :: Python :: 3.7
Classifier: Programming Language :: Python :: 3.8
Classifier: Programming Language :: Python :: 3.9
Classifier: Programming Language :: Python :: 3 :: Only
Classifier: Programming Language :: Python :: Implementation :: CPython
Classifier: Programming Language :: Python :: Implementation :: PyPy
Classifier: Operating System :: OS Independent
Classifier: License :: OSI Approved :: MIT License
Requires-Python: >=3.7
License-File: LICENSE
Requires-Dist: pytest >=7.0.0
Requires-Dist: pyright >=0.0.7
Requires-Dist: pydantic >=1.6.0
